fooster_curse-0.5.1-py3.9-nspkg.pth
fooster/curse/__init__.py
fooster/curse/__main__.py
fooster_curse-0.5.1.dist-info/LICENSE
fooster_curse-0.5.1.dist-info/METADATA
fooster_curse-0.5.1.dist-info/WHEEL
fooster_curse-0.5.1.dist-info/entry_points.txt
fooster_curse-0.5.1.dist-info/namespace_packages.txt
fooster_curse-0.5.1.dist-info/top_level.txt
fooster_curse-0.5.1.dist-info/RECORD
